project_quickstart/__init__.py
project_quickstart/projectQuickstart.py
project_quickstart/project_quickstart.py
project_quickstart/version.py
project_quickstart-0.3.2.dist-info/DESCRIPTION.rst
project_quickstart-0.3.2.dist-info/LICENSE.txt
project_quickstart-0.3.2.dist-info/METADATA
project_quickstart-0.3.2.dist-info/RECORD
project_quickstart-0.3.2.dist-info/WHEEL
project_quickstart-0.3.2.dist-info/entry_points.txt
project_quickstart-0.3.2.dist-info/metadata.json
project_quickstart-0.3.2.dist-info/top_level.txt
templates/.DS_Store
templates/.dir_bash_history
templates/README_data.rst
templates/TO_DO.rst
templates/rsync.rst
templates/examples/.DS_Store
templates/examples/.Rhistory
templates/examples/.dir_bash_history
templates/examples/Dockerfile_pq_example_alpine
templates/examples/Dockerfile_pq_example_ubuntu
templates/examples/README_dockerfiles.rst
templates/examples/__init__.py
templates/examples/examples.sh
templates/examples/ggtheme.R
templates/examples/logging.R
templates/examples/plot_pq_example.py
templates/examples/plot_pq_example_mtcars.R
templates/examples/plot_pq_example_pandas.R
templates/examples/pq_example.R
templates/examples/pq_example.py
templates/examples/pq_example_mtcars.R
templates/examples/svgutils_pq_example.py
templates/examples/version.py
templates/examples/pipeline_pq_example/.DS_Store
templates/examples/pipeline_pq_example/.dir_bash_history
templates/examples/pipeline_pq_example/__init__.py
templates/examples/pipeline_pq_example/pipeline_pq_example.py
templates/examples/pipeline_pq_example/configuration/.DS_Store
templates/examples/pipeline_pq_example/configuration/.dir_bash_history
templates/examples/pipeline_pq_example/configuration/pipeline.yml
templates/examples/pipeline_pq_example/configuration_pipeline_pq_example/.DS_Store
templates/examples/pipeline_pq_example/configuration_pipeline_pq_example/.dir_bash_history
templates/examples/pipeline_pq_example/configuration_pipeline_pq_example/Makefile
templates/examples/pipeline_pq_example/configuration_pipeline_pq_example/conf.py
templates/examples/pipeline_pq_example/configuration_pipeline_pq_example/index.rst
templates/examples/pipeline_pq_example/configuration_pipeline_pq_example/make.bat
templates/examples/pipeline_pq_example/configuration_pipeline_pq_example/pipeline_pq_example.ini
