Metadata-Version: 2.0
Name: project-quickstart
Version: 0.3.2
Summary: Creates template folder and file structure for a Python based data science project.
Home-page: https://github.com/AntonioJBT/project_quickstart
Author: Antonio J Berlanga-Taylor
Author-email: a.berlanga@imperial.ac.uk
License: GPL-3.0
Download-URL: https://github.com/AntonioJBT/project_quickstart.git
Keywords: data science,boilerplate,utility
Platform: 'any'
Classifier: Development Status :: 3 - Alpha
Classifier: Intended Audience :: Science/Research
Classifier: Intended Audience :: Developers
Classifier: License :: OSI Approved
Classifier: Programming Language :: Python
Classifier: Topic :: Software Development
Classifier: Topic :: Scientific/Engineering
Classifier: Topic :: Utilities
Classifier: Operating System :: POSIX
Classifier: Operating System :: Unix
Classifier: Operating System :: MacOS
Requires-Dist: docopt
Requires-Dist: future
